ibwapi/__init__.py
ibwapi/client.py
ibwapi/exceptions.py
ibwapi-0.2.1.dist-info/LICENSE
ibwapi-0.2.1.dist-info/METADATA
ibwapi-0.2.1.dist-info/NOTICE
ibwapi-0.2.1.dist-info/WHEEL
ibwapi-0.2.1.dist-info/top_level.txt
ibwapi-0.2.1.dist-info/RECORD
