Metadata-Version: 2.2
Name: ibwapi
Version: 0.2.1
Summary: A low level, lightweight client for interacting with the Infoblox WAPI
Author-email: Ryan Bolger <ryan-oss@xyto.cc>
Project-URL: Homepage, https://github.com/rmbolger/py-ibwapi
Project-URL: Documentation, https://github.com/rmbolger/py-ibwapi
Project-URL: Source, https://github.com/rmbolger/py-ibwapi
Keywords: infoblox,nios,wapi,ddi,rest
Classifier: Development Status :: 4 - Beta
Classifier: License :: OSI Approved :: MIT License
Classifier: Intended Audience :: Information Technology
Classifier: Intended Audience :: System Administrators
Classifier: Environment :: Web Environment
Classifier: Natural Language :: English
Classifier: Operating System :: OS Independent
Classifier: Programming Language :: Python
Classifier: Programming Language :: Python :: 3
Classifier: Programming Language :: Python :: 3.8
Classifier: Programming Language :: Python :: 3.9
Classifier: Programming Language :: Python :: 3.10
Classifier: Programming Language :: Python :: 3.11
Classifier: Programming Language :: Python :: 3.12
Classifier: Programming Language :: Python :: 3.13
Classifier: Programming Language :: Python :: 3 :: Only
Classifier: Topic :: Software Development :: Libraries
Classifier: Topic :: Internet :: Name Service (DNS)
Classifier: Topic :: System :: Networking
Requires-Python: >=3.8
License-File: LICENSE
License-File: NOTICE
Requires-Dist: requests>=2.32.2
